sphinx_doxysummary/__init__.py
sphinx_doxysummary/directive.py
sphinx_doxysummary/generate.py
sphinx_doxysummary/utils.py
sphinx_doxysummary/xmltree.py
sphinx_doxysummary/templates/cppbase.rst
sphinx_doxysummary-2.3.4.dist-info/METADATA
sphinx_doxysummary-2.3.4.dist-info/WHEEL
sphinx_doxysummary-2.3.4.dist-info/top_level.txt
sphinx_doxysummary-2.3.4.dist-info/RECORD
