Metadata-Version: 2.1
Name: sphinx-doxysummary
Version: 2.3.4
Summary: Sphinx extension for Doxygen entries.
Home-page: https://github.com/quocdang1998/doxysummary
Author: Dinh Quoc Dang Nguyen
Author-email: quocdang1998@gmail.com
License: MIT
Keywords: Sphinx,autosummary,Doxygen
Platform: Microsoft :: Windows
Platform: POSIX :: Linux
Classifier: Framework :: Sphinx :: Extension
Classifier: License :: OSI Approved :: MIT License
Classifier: Operating System :: OS Independent
Classifier: Programming Language :: C++
Classifier: Programming Language :: Python :: 3.6
Classifier: Programming Language :: Python :: 3.7
Classifier: Programming Language :: Python :: 3.8
Classifier: Programming Language :: Python :: 3.9
Classifier: Programming Language :: Python :: 3.10
Classifier: Programming Language :: Python :: 3.11
Classifier: Programming Language :: Python :: 3.12
Classifier: Topic :: Documentation :: Sphinx
Requires-Python: >=3.6
Requires-Dist: Sphinx >=4.0.0
Requires-Dist: lxml >=4.9
Provides-Extra: example
Requires-Dist: breathe >=4.34 ; extra == 'example'
Requires-Dist: sphinx-rtd-theme ; extra == 'example'
